LICENSE
MANIFEST.in
README.md
setup.py
sedobs/Check_plots.py
sedobs/Photometry.py
sedobs/Spectroscopy.py
sedobs/__info__.py
sedobs/__main__.py
sedobs/atmosphere.py
sedobs/cli.py
sedobs/config.py
sedobs/cosmo.py
sedobs/filters.py
sedobs/library.py
sedobs/messages.py
sedobs/modif_LIB.py
sedobs/simu.py
sedobs/simu_output.py
sedobs/units.py
sedobs.egg-info/PKG-INFO
sedobs.egg-info/SOURCES.txt
sedobs.egg-info/dependency_links.txt
sedobs.egg-info/entry_points.txt
sedobs.egg-info/requires.txt
sedobs.egg-info/top_level.txt
sedobs/docs/.nojekyll
sedobs/docs/Makefile
sedobs/docs/index.html
sedobs/docs/build/doctrees/MultiSpectro.doctree
sedobs/docs/build/doctrees/Spectro.doctree
sedobs/docs/build/doctrees/atmospheric.doctree
sedobs/docs/build/doctrees/configuration.doctree
sedobs/docs/build/doctrees/environment.pickle
sedobs/docs/build/doctrees/filters.doctree
sedobs/docs/build/doctrees/full.doctree
sedobs/docs/build/doctrees/index.doctree
sedobs/docs/build/doctrees/installation.doctree
sedobs/docs/build/doctrees/output.doctree
sedobs/docs/build/doctrees/photo.doctree
sedobs/docs/build/doctrees/tests.doctree
sedobs/docs/build/doctrees/usage.doctree
sedobs/docs/build/html/.buildinfo
sedobs/docs/build/html/.nojekyll
sedobs/docs/build/html/MultiSpectro.html
sedobs/docs/build/html/Spectro.html
sedobs/docs/build/html/atmospheric.html
sedobs/docs/build/html/configuration.html
sedobs/docs/build/html/filters.html
sedobs/docs/build/html/full.html
sedobs/docs/build/html/genindex.html
sedobs/docs/build/html/index.html
sedobs/docs/build/html/installation.html
sedobs/docs/build/html/objects.inv
sedobs/docs/build/html/output.html
sedobs/docs/build/html/photo.html
sedobs/docs/build/html/search.html
sedobs/docs/build/html/searchindex.js
sedobs/docs/build/html/tests.html
sedobs/docs/build/html/usage.html
sedobs/docs/build/html/_downloads/SEDobs_filters.hdf5
sedobs/docs/build/html/_downloads/7c9095393e5569bc38ae26711b770d1e/SEDobs_filters.hdf5
sedobs/docs/build/html/_images/2mass.png
sedobs/docs/build/html/_images/AKARI.png
sedobs/docs/build/html/_images/CFHT_megaprime.png
sedobs/docs/build/html/_images/CSP.png
sedobs/docs/build/html/_images/EFOSC.png
